terndata/ecoplots/__init__.py
terndata/ecoplots/_base.py
terndata/ecoplots/_config.py
terndata/ecoplots/_exceptions.py
terndata/ecoplots/_nlp_utils.py
terndata/ecoplots/_utils.py
terndata/ecoplots/ecoplots.py
terndata/ecoplots/version.py
terndata/ecoplots/_flatten_response/__init__.py
terndata/ecoplots/_flatten_response/_streaming.py
terndata/ecoplots/_flatten_response/_workers.py
terndata/ecoplots/_gui/__init__.py
terndata/ecoplots/_gui/spatial_selector.py
terndata/ecoplots/assets/TERN_logo.png
terndata/ecoplots/assets/ecoplots_logo.svg
terndata_ecoplots-0.0.3b2.dist-info/licenses/LICENSE
terndata_ecoplots-0.0.3b2.dist-info/licenses/NOTICE
terndata_ecoplots-0.0.3b2.dist-info/METADATA
terndata_ecoplots-0.0.3b2.dist-info/WHEEL
terndata_ecoplots-0.0.3b2.dist-info/top_level.txt
terndata_ecoplots-0.0.3b2.dist-info/RECORD
