Metadata-Version: 2.4
Name: terndata.ecoplots
Version: 0.0.3b2
Summary: TERN ecoplots data access library
Author-email: Avinash Chandra <avinash.chandra@uq.edu.au>
Maintainer-email: "TERN Data Services and Analytics (TDSA)" <esupport@tern.org.au>
License-Expression: Apache-2.0
Project-URL: Home, https://github.com/ternaustralia/terndata.ecoplots
Project-URL: Documentation, https://terndata-ecoplots.readthedocs.io
Classifier: Development Status :: 4 - Beta
Classifier: Intended Audience :: Education
Classifier: Intended Audience :: Science/Research
Classifier: Programming Language :: Python
Classifier: Programming Language :: Python :: 3
Classifier: Programming Language :: Python :: 3.10
Classifier: Programming Language :: Python :: 3.11
Classifier: Programming Language :: Python :: 3.12
Classifier: Programming Language :: Python :: 3.13
Classifier: Topic :: Software Development :: Libraries :: Python Modules
Requires-Python: >=3.10
License-File: LICENSE
License-File: NOTICE
Requires-Dist: typing-extensions
Requires-Dist: numpy
Requires-Dist: pandas
Requires-Dist: geopandas
Requires-Dist: requests
Requires-Dist: python-dateutil
Requires-Dist: pytz
Requires-Dist: httpx<1.0.0,>=0.28.1
Requires-Dist: rapidfuzz<4.0.0,>=3.13.0
Requires-Dist: orjson<4.0.0,>=3.10.15
Requires-Dist: diskcache<6.0.0,>=5.6.3
Requires-Dist: ijson<4.0.0,>=3.4.0
Requires-Dist: defusedxml<1.0.0,>=0.7.1
Requires-Dist: shapely<3.0.0,>=2.0.0
Requires-Dist: ipyleaflet<1.0.0,>=0.20.0
Requires-Dist: ipywidgets<9.0.0,>=8.1.7
Dynamic: license-file
